MANIFEST.in
README.rst
setup.py
aliyun_python_sdk_webplus.egg-info/PKG-INFO
aliyun_python_sdk_webplus.egg-info/SOURCES.txt
aliyun_python_sdk_webplus.egg-info/dependency_links.txt
aliyun_python_sdk_webplus.egg-info/requires.txt
aliyun_python_sdk_webplus.egg-info/top_level.txt
aliyunsdkwebplus/__init__.py
aliyunsdkwebplus/endpoint.py
aliyunsdkwebplus/request/__init__.py
aliyunsdkwebplus/request/v20190320/AbortChangeRequest.py
aliyunsdkwebplus/request/v20190320/CreateAppEnvRequest.py
aliyunsdkwebplus/request/v20190320/CreateApplicationRequest.py
aliyunsdkwebplus/request/v20190320/CreateConfigTemplateRequest.py
aliyunsdkwebplus/request/v20190320/CreatePkgVersionRequest.py
aliyunsdkwebplus/request/v20190320/CreateStorageRequest.py
aliyunsdkwebplus/request/v20190320/DeleteAppEnvRequest.py
aliyunsdkwebplus/request/v20190320/DeleteApplicationRequest.py
aliyunsdkwebplus/request/v20190320/DeleteChangeRequest.py
aliyunsdkwebplus/request/v20190320/DeleteConfigTemplateRequest.py
aliyunsdkwebplus/request/v20190320/DeletePkgVersionRequest.py
aliyunsdkwebplus/request/v20190320/DescribeAppEnvInstanceHealthRequest.py
aliyunsdkwebplus/request/v20190320/DescribeAppEnvStatusRequest.py
aliyunsdkwebplus/request/v20190320/DescribeAppEnvsRequest.py
aliyunsdkwebplus/request/v20190320/DescribeApplicationsRequest.py
aliyunsdkwebplus/request/v20190320/DescribeCategoriesRequest.py
aliyunsdkwebplus/request/v20190320/DescribeChangeRequest.py
aliyunsdkwebplus/request/v20190320/DescribeChangesRequest.py
aliyunsdkwebplus/request/v20190320/DescribeConfigIndexRequest.py
aliyunsdkwebplus/request/v20190320/DescribeConfigOptionsRequest.py
aliyunsdkwebplus/request/v20190320/DescribeConfigSettingsRequest.py
aliyunsdkwebplus/request/v20190320/DescribeConfigTemplatesRequest.py
aliyunsdkwebplus/request/v20190320/DescribeEnvResourceRequest.py
aliyunsdkwebplus/request/v20190320/DescribeEventsRequest.py
aliyunsdkwebplus/request/v20190320/DescribeGatherLogResultRequest.py
aliyunsdkwebplus/request/v20190320/DescribeGatherStatsResultRequest.py
aliyunsdkwebplus/request/v20190320/DescribeInstanceHealthRequest.py
aliyunsdkwebplus/request/v20190320/DescribePkgVersionsRequest.py
aliyunsdkwebplus/request/v20190320/DescribeStacksRequest.py
